{
  "meta": {
    "title": "2026학년도 1학년 동아리 활동",
    "year": "2026"
  },
  "students": {
    "10102": {
      "club": "G평선(인문사회)",
      "activities": [
        {
          "date": "2026",
          "type": "토론",
          "title": "호르무즈 해협 파병 찬반 토론",
          "summary": "호르무즈 해협 해군 파병 논제에 대해 찬반 양측 입론을 작성함. 찬성 측에서는 한국 수입 원유의 70%가 중동산이며 95%가 호르무즈 해협을 경유한다는 통계를 근거로 에너지 안보와 국익 수호를 위한 파병의 필요성을 논증하고, 유엔해양법협약 제38조의 통과통항권을 법적 근거로 제시함. 반대 측에서는 2021년 MT한국케미호 나포 사건을 실증적 사례로 들어 군사 개입이 초래할 외교적 리스크와 자국민 안전 위협을 지적하고, 헌법 제60조 제2항의 국회 동의 절차 위반 가능성을 법리적으로 비판함. 영국·프랑스 등 주요 우방국의 신중한 태도를 비교 근거로 활용하는 등 다각도의 논거를 구성함.",
          "keywords": [
            "에너지안보",
            "국제법",
            "헌법",
            "외교리스크",
            "찬반토론"
          ]
        },
        {
          "date": "2026",
          "type": "모의유엔",
          "title": "유엔 안전보장이사회 - 호르무즈 해협 통행료 문제 (영국 대표)",
          "summary": "유엔 안전보장이사회 모의 활동에서 영국 대표를 맡아 호르무즈 해협 통행료 강제 징수 문제에 대한 영국의 입장을 논리적으로 개진함. 안보리의 구조와 의결 방식(상임이사국 5개국 거부권, 15개국 중 9개국 찬성 요건)을 정확히 이해하고, UNCLOS(유엔 해양법 협약)를 근거로 국제 해협에서의 통행료 부과는 명백한 국제법 위반임을 논증함. 특정 국가의 경제적 협박으로부터 자국 상선과 국제 무역로를 보호하기 위해 동맹국과의 공조를 강조하고, 국제사회의 결속을 촉구하는 영국 대표단 성명을 발표함. 단순 군사적 관점을 넘어 경제적 볼모 문제로 논점을 확장하는 시각을 보임.",
          "keywords": [
            "모의유엔",
            "안보리",
            "UNCLOS",
            "항행의자유",
            "국제법",
            "영국대표"
          ]
        }
      ]
    },
    "10104": {
      "club": "에듀브릿지(교육)",
      "activities": [
        {
          "date": "2026",
          "type": "토론",
          "title": "운동은 약을 대체할 수 있는가",
          "summary": "에듀브릿지 동아리 토론 활동에서 '운동은 약을 대체할 수 있는가'를 주제로 찬성 측 입장을 맡아 핵심 논리 구성과 반박을 주도함. 운동이 질병의 증상만을 관리하는 약물과 달리 신체 자생력을 높이고 근본 원인을 해결한다는 생화학적 근거를 제시하고, 규칙적 유산소 운동이 인슐린 저항성 개선과 심혈관 질환 예방에 미치는 효과를 구체적 사례로 논증함. 반대 측의 '급성 질환에는 약이 필수적'이라는 주장에 대해 운동의 예방적 기능과 만성질환 치료 효과를 분리하여 반박하고, '완전 대체'가 아닌 '대체 가능한 영역의 확장'으로 논지를 정교화함. 토론 후 운동과 의학의 상호보완적 역할을 깊이 이해하는 성과를 얻음.",
          "keywords": [
            "운동생리학",
            "만성질환",
            "찬반토론",
            "논리구성",
            "반박"
          ]
        }
      ]
    },
    "10113": {
      "club": "에듀브릿지(교육)",
      "activities": [
        {
          "date": "2026",
          "type": "토론",
          "title": "수학 교육에서 공식 암기는 필요한가",
          "summary": "에듀브릿지 동아리 토론 활동에서 '수학 교육에서 공식 암기는 필요한가'를 주제로 찬성 측 입론 발표를 담당함. 제한된 시간 내 문제 해결이 요구되는 수능·모의고사 환경에서 공식 암기가 풀이 속도와 정확도를 높이는 실질적 도구임을 주장하고, 반복 암기가 수학적 패턴 인식 능력을 강화한다는 인지과학적 근거를 제시함. 반대 측의 '개념 이해 없는 암기는 응용력을 저해한다'는 주장에 대해 암기와 이해가 상호 배타적이지 않고 상호 보완적임을 논리적으로 반박함. 직접 조사한 자료를 바탕으로 발표를 진행하며 논거를 구체화하는 과정에서 비판적 사고력과 논리적 표현 역량을 기름.",
          "keywords": [
            "수학교육",
            "공식암기",
            "찬반토론",
            "인지과학",
            "논증"
          ]
        }
      ]
    },
    "10123": {
      "club": "에듀브릿지(교육)",
      "activities": [
        {
          "date": "2026",
          "type": "토론",
          "title": "수능 영어 절대평가는 학습 동기를 떨어뜨리는가",
          "summary": "에듀브릿지 동아리 토론 활동에서 '수능 영어 절대평가는 학습 동기를 떨어뜨리는가'를 주제로 찬성 측 입장에서 자료조사와 발표를 담당함. 절대평가 도입 이후 등급 경쟁 완화로 학생들의 결과 불안이 감소하고 실제 언어 활용 능력에 집중할 수 있는 환경이 조성되었다는 근거를 제시함. 영어 학습의 목적을 점수 획득에서 실질적 의사소통 능력 함양으로 전환하는 것이 교육적으로 바람직하다는 논지를 전개함. 자료조사를 통해 교육 정책의 효과를 다각도로 분석하는 과정에서 교육학적 탐구 역량과 논증 능력을 신장함.",
          "keywords": [
            "수능영어",
            "절대평가",
            "교육정책",
            "학습동기",
            "찬반토론"
          ]
        }
      ]
    },
    "10213": {
      "club": "에듀브릿지(교육)",
      "activities": [
        {
          "date": "2026",
          "type": "토론",
          "title": "수학 교육에서 공식 암기는 여전히 필요한가",
          "summary": "에듀브릿지 동아리 토론 활동에서 '수학 교육에서 공식 암기는 여전히 필요한가'를 주제로 찬성 측 입장에서 자료조사와 발표를 맡음. 복잡한 문제를 풀 때 공식 암기가 풀이 속도를 높여 한정된 시험 시간 내 효율적인 문제 해결을 가능하게 한다는 실용적 근거를 논증함. 반대 측의 개념 이해 중심 주장에 대해 이해와 암기가 병행될 때 수학적 사고력이 극대화됨을 논리적으로 반박하고, 팀 토론에서 상대방의 의견을 경청하며 논리적으로 재반론하는 방식으로 토론을 이끔. 토론 활동을 통해 수학 교육의 목적과 방법론에 대해 깊이 성찰하는 계기를 마련함.",
          "keywords": [
            "수학교육",
            "공식암기",
            "찬반토론",
            "논리반박",
            "교육방법론"
          ]
        }
      ]
    },
    "10222": {
      "club": "에듀브릿지(교육)",
      "activities": [
        {
          "date": "2026",
          "type": "토론",
          "title": "교사의 교권 보호와 학생의 권리 보장 중 무엇이 우선인가",
          "summary": "에듀브릿지 동아리 토론 활동에서 '교권 보호와 학생 권리 보장 중 무엇이 우선인가'를 주제로 교권 보호 우선 입장에서 자료조사와 발표·입론을 담당함. 학교폭력 초기 교사 개입이 차단될 경우 피해 확산으로 이어질 수 있다는 구체적 사례를 제시하며 교권 약화가 교육 현장 전반에 미치는 부정적 영향을 논증함. 상대 측의 학생 인권 우선 주장에 대해 교권과 학생 인권이 대립 구도가 아닌 교육 공동체의 상호 보완적 가치임을 강조하며 반박함. 교육 관련 법제도를 탐구하는 과정에서 교육학적 사고력과 균형 잡힌 논거 구성 역량을 기름.",
          "keywords": [
            "교권보호",
            "학생인권",
            "교육법",
            "찬반토론",
            "교육공동체"
          ]
        }
      ]
    },
    "10225": {
      "club": "에듀브릿지(교육)",
      "activities": [
        {
          "date": "2026",
          "type": "토론",
          "title": "운동은 약을 대체할 수 있는가",
          "summary": "에듀브릿지 동아리 토론 활동에서 '운동은 약을 대체할 수 있는가'를 주제로 찬성 측에서 자료조사와 발표를 담당함. 운동이 신체적·정신적 건강을 향상시켜 일부 만성질환 관리에서 약물에 준하는 효과를 발휘한다는 근거를 제시하고, 규칙적인 유산소 운동이 혈압·혈당 조절에 미치는 임상적 효과를 논증함. 반대 측의 '급성 질환에는 운동이 대체 불가'라는 주장에 대해 '완전 대체'가 아닌 '예방과 보완'의 관점으로 논지를 조정하여 반박하는 유연한 논리 전개를 보임. 입론과 반론을 통해 과학적 근거를 기반으로 논거를 구성하는 역량을 기름.",
          "keywords": [
            "운동생리학",
            "만성질환",
            "약물대체",
            "찬반토론",
            "논증"
          ]
        }
      ]
    },
    "10410": {
      "club": "에듀브릿지(교육)",
      "activities": [
        {
          "date": "2026",
          "type": "토론",
          "title": "교권과 학생 인권 중 무엇이 더 중요한가",
          "summary": "에듀브릿지 동아리 토론 활동에서 '교권과 학생 인권 중 무엇이 더 중요한가'를 주제로 학생 인권 우선 입장에서 자료조사와 발표·입론을 담당함. 미성년자인 학생은 학교 내 가장 취약한 존재로 안전하고 평등한 학습 환경을 보장받을 권리가 제도적으로 우선 보호되어야 함을 논증하고, 사회적·제도적 권력 불균형 속에서 학생 권리 보장의 중요성을 사례로 제시함. 상대 측 주장에 대해 교권과 학생 인권이 상호 보완적 관계임을 인정하면서도 구조적 취약성을 근거로 학생 보호의 우선순위를 논리적으로 방어함. 입론과 반박을 통해 교육 관련 법제도를 탐구하는 역량을 기름.",
          "keywords": [
            "학생인권",
            "교권",
            "교육법",
            "찬반토론",
            "권리우선순위"
          ]
        }
      ]
    },
    "10416": {
      "club": "에듀브릿지(교육)",
      "activities": [
        {
          "date": "2026",
          "type": "토론",
          "title": "수능 영어 절대평가는 학습 동기를 떨어뜨리는가",
          "summary": "에듀브릿지 동아리 토론 활동에서 '수능 영어 절대평가는 학습 동기를 떨어뜨리는가'를 주제로 찬반 양측 자료를 조사하고 반박 논리를 구성하는 역할을 담당함. DBpia 등재 이지연 연구를 인용하여 절대평가 도입 후 학습 동기와 목표의 질이 약화되는 부작용이 나타났다는 실증적 근거를 제시함. 찬반 양측 주장을 균형 있게 정리하고 근거를 바탕으로 반박 논리를 구성하여 팀의 설득력을 높이는 기여를 함. 학술 논문을 활용한 실증적 논거 탐색 경험을 통해 교육 정책을 비판적으로 분석하는 안목과 탐구 역량을 기름.",
          "keywords": [
            "수능영어",
            "절대평가",
            "교육정책",
            "실증연구",
            "비판적사고"
          ]
        }
      ]
    },
    "10427": {
      "club": "에듀브릿지(교육)",
      "activities": [
        {
          "date": "2026",
          "type": "토론",
          "title": "능력 중심 사회는 옳은가",
          "summary": "에듀브릿지 동아리 토론 활동에서 '능력 중심 사회는 옳은가'를 주제로 찬성 측에서 역사적 근거 탐색과 발표를 담당함. 조선시대 과거제가 신분 중심 구조를 완화하고 능력 기반 인재 선발로 국가 운영의 효율성을 높인 역사적 사례를 논거로 제시하고, 능력주의가 기회의 평등을 구현하는 제도적 기반이 된다는 논지를 전개함. 상대 측의 능력주의 한계 지적에 대해 '완전 폐지'가 아닌 '포용적 능력주의'로의 발전 방향을 제안하는 유연한 결론을 도출함. 역사·사회 자료를 분석하고 통합적으로 논거를 구성하는 과정에서 인문사회적 탐구 역량을 기름.",
          "keywords": [
            "능력주의",
            "과거제",
            "사회제도",
            "찬반토론",
            "역사적근거"
          ]
        }
      ]
    },
    "10508": {
      "club": "에듀브릿지(교육)",
      "activities": [
        {
          "date": "2026",
          "type": "토론",
          "title": "능력 중심 사회가 옳은가",
          "summary": "에듀브릿지 동아리 토론 활동에서 '능력 중심 사회가 옳은가'를 주제로 찬성 측에서 자료조사를 담당함. 사회가 개인의 신분이나 배경이 아닌 노력과 능력을 기준으로 인재를 선발할 때 기회의 평등과 사회적 효율성이 높아진다는 근거를 제시하고, 능력 중심 평가가 계층 이동의 사다리 역할을 수행한다는 논지를 전개함. 상대 측의 능력주의 한계 주장에 대해 '포용적 능력주의' 개념으로 반박하며, 능력에 따른 평가는 필요하되 사회적 약자에 대한 구조적 보완 장치가 병행되어야 한다는 균형 잡힌 결론을 도출함. 자료조사와 발표를 통해 사회 구조에 대한 비판적 사고력을 기름.",
          "keywords": [
            "능력주의",
            "기회평등",
            "사회구조",
            "찬반토론",
            "포용적능력주의"
          ]
        }
      ]
    },
    "10519": {
      "club": "에듀브릿지(교육)",
      "activities": [
        {
          "date": "2026",
          "type": "토론",
          "title": "운동은 약을 대체할 수 있는가",
          "summary": "에듀브릿지 동아리 토론 활동에서 '운동은 약을 대체할 수 있는가'를 주제로 찬성 측에서 자료조사와 발표를 담당함. 약을 복용하는 근본 이유인 질병 예방과 치료의 관점에서 규칙적인 운동이 다수의 만성질환에 대해 약물과 유사하거나 그 이상의 예방·개선 효과를 발휘한다는 의학적 근거를 논증함. 상대 측의 '급성·중증 질환에는 운동이 대체 불가'라는 주장을 인정하면서도 예방과 만성질환 관리 영역에서의 대체 가능성을 강조하는 논리적 경계 설정으로 찬성 입장을 방어함. 주장과 근거를 구체적으로 발표하며 의학·생명과학적 논거 구성 역량을 기름.",
          "keywords": [
            "운동처방",
            "만성질환",
            "약물대체",
            "찬반토론",
            "의학적근거"
          ]
        }
      ]
    },
    "10817": {
      "club": "에듀브릿지(교육)",
      "activities": [
        {
          "date": "2026",
          "type": "토론",
          "title": "수학 교육에서 공식 암기는 여전히 필요한가",
          "summary": "에듀브릿지 동아리 토론 활동에서 '수학 교육에서 공식 암기는 여전히 필요한가'를 주제로 반대 측에서 자료조사와 발표·반론을 담당함. 공식 암기보다 수학적 원리와 개념 이해를 중심으로 한 학습이 진정한 응용력과 문제 해결 능력을 기른다는 논지를 전개하고, 공식이 어떤 원리에 의해 도출되는지 이해하지 못한 채 암기만 하면 변형 문제에서 한계가 드러난다는 근거를 제시함. 찬성 측의 실용적 효율성 주장에 대해 이해 중심 학습이 장기적으로 더 효율적임을 반박하며 적극적으로 논증함. 자료조사·발표·반론을 두루 수행하며 수학 교육의 본질에 대한 비판적 사고력을 기름.",
          "keywords": [
            "수학교육",
            "개념이해",
            "공식암기",
            "찬반토론",
            "비판적사고"
          ]
        }
      ]
    },
    "10108": {
      "club": "프로토타입(공학)",
      "activities": [
        {
          "date": "2026",
          "type": "동아리",
          "title": "프로토타입 동아리 활동 - 희망학과 발표 및 AI 독서토론",
          "summary": "프로토타입 동아리에 참여하여 공학 계열 진로 탐색 활동을 수행함. 1차 활동에서는 팀원들과 함께 희망학과를 조사하고 발표하는 활동에 참여하며 다양한 공학 분야의 특성을 이해하는 계기를 가짐. 2차 활동에서는 아이작 아시모프의 『아이, 로봇』을 선정하여 AI의 무한한 발전에 대한 찬반 토론을 준비하고, 인공지능 기술이 미래 사회에 미치는 영향을 다각도로 탐구하는 독서토론 활동에 참여함. 공학과 AI 기술에 대한 관심을 바탕으로 진로를 탐색하는 경험을 쌓음.",
          "keywords": [
            "공학진로탐색",
            "희망학과발표",
            "AI독서토론",
            "아이로봇"
          ]
        }
      ]
    },
    "10602": {
      "club": "프로토타입(공학)",
      "activities": [
        {
          "date": "2026",
          "type": "동아리",
          "title": "프로토타입 동아리 활동 - 기계공학 발표 및 AI 독서토론",
          "summary": "프로토타입 동아리에서 기계공학 관련 직업을 진로로 탐색하며 활동함. 1차 활동에서 『공학이란 무엇인가』를 읽고 기계공학 분야의 내용을 조사하여 PPT를 제작하고 발표하는 역할을 담당함. 기계공학의 핵심 원리와 직업 세계를 정리하며 희망 진로에 대한 이해를 심화함. 2차 활동에서는 아이작 아시모프의 『아이, 로봇』을 감상하고 AI의 무한한 발전에 대한 찬반 입장을 정하여 독서토론을 준비함. 공학 분야의 폭넓은 탐색과 AI 기술에 대한 비판적 사고력을 기름.",
          "keywords": [
            "기계공학",
            "PPT발표",
            "공학이란무엇인가",
            "AI독서토론",
            "아이로봇"
          ]
        }
      ]
    },
    "10608": {
      "club": "프로토타입(공학)",
      "activities": [
        {
          "date": "2026",
          "type": "동아리",
          "title": "프로토타입 동아리 활동 - 뉴럴링크 발표 및 AI 독서토론",
          "summary": "프로토타입 동아리에서 자동차공학자를 진로로 삼아 활동함. 1차 활동에서 '대한민국 헌법 제1조' 조의 생물화학공학 주제 발표 시간에 뇌-컴퓨터 인터페이스 기술인 '뉴럴링크'를 조사하여 발표함. 뉴럴링크의 작동 원리, 의료·공학적 적용 가능성, 윤리적 쟁점을 탐구하며 공학과 생명과학의 융합 사례를 이해함. 2차 독서토론에서 『아이, 로봇』을 읽고 'AI 무한 발전' 주제에 반대 입장을 취하여 AI 과의존으로 인한 인간 자율성 약화와 부정적 결과를 논거로 제시함. 공학 기술의 사회적 영향을 비판적으로 탐구하는 역량을 기름.",
          "keywords": [
            "뉴럴링크",
            "뇌컴퓨터인터페이스",
            "AI독서토론",
            "아이로봇",
            "AI발전반대"
          ]
        }
      ]
    },
    "10618": {
      "club": "프로토타입(공학)",
      "activities": [
        {
          "date": "2026",
          "type": "동아리",
          "title": "프로토타입 동아리 활동 - 전자공학 발표 및 AI 독서토론",
          "summary": "프로토타입 동아리에서 과학 연구원을 진로로 삼아 활동함. 1차 활동에서 조 내 전자공학을 주제로 전자공학의 역사·신기술·주요 인물을 조사하고 발표를 담당함. 전자공학이 현대 산업 전반에 미치는 영향을 탐구하며 공학 연구원으로서 필요한 지식의 폭을 넓힘. 2차 독서토론에서 『아이, 로봇』을 읽고 'AI의 무한한 발전이 인간에게 긍정적인가'를 주제로 반대 입장에서 경제적 불평등, 인간 존엄성 상실, 환경 파괴 등 AI 과발전의 부작용을 논거로 제시함. 공학 기술의 사회적 책임을 탐구하며 비판적 사고력을 기름.",
          "keywords": [
            "전자공학",
            "AI독서토론",
            "아이로봇",
            "AI발전반대",
            "공학연구원"
          ]
        }
      ]
    },
    "10624": {
      "club": "프로토타입(공학)",
      "activities": [
        {
          "date": "2026",
          "type": "동아리",
          "title": "프로토타입 동아리 활동 - 반도체공학 발표 및 AI 독서토론",
          "summary": "프로토타입 동아리에서 반도체공학자를 진로로 삼아 활동함. 1차 활동에서 반도체공학에 대한 자료를 조사하여 반도체 소자의 원리, 제조 공정, 미래 산업에서의 역할을 탐구하고 팀 발표에 기여함. 반도체가 현대 전자기기와 AI 시스템의 핵심 부품임을 이해하는 계기가 됨. 2차 독서토론에서 『아이, 로봇』을 읽고 'AI의 무한한 발전 찬성' 입장을 취하여 AI가 반도체 기술 발전과 결합하여 인류의 문제 해결에 기여할 수 있다는 논거를 제시함. 공학 진로와 AI 기술의 연관성을 탐구하며 공학적 사고력을 기름.",
          "keywords": [
            "반도체공학",
            "AI독서토론",
            "아이로봇",
            "AI발전찬성",
            "공학탐구"
          ]
        }
      ]
    },
    "10705": {
      "club": "프로토타입(공학)",
      "activities": [
        {
          "date": "2026",
          "type": "동아리",
          "title": "프로토타입 동아리 활동 - 희망학과 발표 및 AI 독서토론 준비",
          "summary": "프로토타입 동아리에서 대기업 임원을 진로로 삼아 활동함. 1차 활동에서 『공학이란 무엇인가』를 읽고 팀원들과 각자 희망학과를 분담하여 소개하는 발표를 진행함. 공학 계열 학과들의 특성과 산업 연관성을 탐구하며 대기업 연구·경영 분야로 이어지는 공학적 기초를 이해하는 시간을 가짐. 2차 활동에서는 『아이, 로봇』을 바탕으로 AI 발전에 대한 찬반 입장을 정하고 팀 토론 방향을 구성하는 준비 활동을 수행함. 공학 분야와 AI 기술이 미래 경영 환경에 미치는 영향을 탐색하며 융합적 사고력을 기름.",
          "keywords": [
            "희망학과발표",
            "공학이란무엇인가",
            "AI독서토론",
            "아이로봇",
            "공학탐구"
          ]
        }
      ]
    },
    "10707": {
      "club": "프로토타입(공학)",
      "activities": [
        {
          "date": "2026",
          "type": "동아리",
          "title": "프로토타입 동아리 활동 - 항공우주공학 발표 및 AI 독서토론",
          "summary": "프로토타입 동아리에서 항공우주공학기술자를 진로로 삼아 활동함. 1차 활동에서 팀 내 항공우주공학과를 맡아 학과 특성, 연구 분야, 진출 경로를 조사하여 발표를 준비하고 수행함. 우주발사체·항공기 개발에 필요한 공학적 원리를 탐구하며 희망 진로에 대한 구체적 이해를 심화함. 2차 독서토론에서 『아이, 로봇』을 읽고 AI의 무한한 발전에 대해 반대 입장을 취하여 일자리 감소·통제 불가능성·인간성 상실이라는 세 가지 논거를 체계적으로 구성함. 공학 기술의 발전 방향과 사회적 영향을 비판적으로 분석하는 역량을 기름.",
          "keywords": [
            "항공우주공학",
            "AI독서토론",
            "아이로봇",
            "AI발전반대",
            "진로탐색"
          ]
        }
      ]
    },
    "10710": {
      "club": "프로토타입(공학)",
      "activities": [
        {
          "date": "2026",
          "type": "동아리",
          "title": "프로토타입 동아리 활동 - 공학 자료조사 및 AI 독서토론",
          "summary": "프로토타입 동아리에서 기계공학·전자공학을 진로로 탐색하며 활동함. 1차 활동에서 팀 내 공학 분야 자료를 조사하고 정리하는 역할을 담당하며 기계공학과 전자공학의 원리와 적용 사례를 탐구함. 2차 독서토론에서 『아이, 로봇』을 감상하고 AI의 긍정적·부정적 관점을 분석한 뒤 반대 입장을 취하여 'AI의 무한한 발전은 위험하다'는 논지를 전개함. AI가 초래할 수 있는 통제 불가능성과 사회적 불안을 논거로 제시하며 공학 기술의 발전과 윤리적 한계에 대해 비판적으로 사고하는 역량을 기름.",
          "keywords": [
            "기계공학",
            "전자공학",
            "AI독서토론",
            "아이로봇",
            "AI발전반대"
          ]
        }
      ]
    },
    "10723": {
      "club": "프로토타입(공학)",
      "activities": [
        {
          "date": "2026",
          "type": "동아리",
          "title": "프로토타입 동아리 활동 - AI 독서토론",
          "summary": "프로토타입 동아리에서 기계공학·생명공학·전자공학 분야에 관심을 가지고 활동함. 어릴 때부터 공학 분야에 흥미를 가져왔으며 동아리 활동을 통해 구체적인 진로 방향을 탐색함. 독서토론 활동에서 『아이, 로봇』을 읽고 'AI의 무한한 발전 찬성' 입장을 취하여 인류가 직면한 복잡한 문제를 해결하는 데 AI의 지능이 필수적이라는 논거를 제시함. AI가 의료·환경·공학 분야에서 인간의 능력을 확장하는 도구로서 기능할 때 사회적 이익이 크다는 논지를 전개하며, 공학과 AI 기술의 융합 가능성에 대한 관심과 탐구 역량을 기름.",
          "keywords": [
            "공학진로탐색",
            "AI독서토론",
            "아이로봇",
            "AI발전찬성",
            "기계공학"
          ]
        }
      ]
    },
    "10914": {
      "club": "프로토타입(공학)",
      "activities": [
        {
          "date": "2026",
          "type": "동아리",
          "title": "프로토타입 동아리 활동 - 항공우주공학 자료조사 및 AI 독서토론",
          "summary": "프로토타입 동아리에서 공학 계열 진학을 목표로 활동함. 1차 활동에서 팀 내 항공우주공학 분야의 자료조사를 담당하여 항공기·우주발사체 개발 원리와 항공우주 산업 동향을 탐구함. 공학 진로에 대한 구체적 이해를 넓히는 계기를 마련함. 2차 독서토론에서 『아이, 로봇』을 읽고 AI의 무한한 발전에 반대 입장을 취하여 AI 반란·일자리 감소·위험성 등을 입론 근거로 삼아 자료를 조사하고 논거를 구성함. AI 기술의 발전 가능성과 사회적 위험성을 균형 있게 분석하며 공학적·비판적 사고력을 기름.",
          "keywords": [
            "항공우주공학",
            "AI독서토론",
            "아이로봇",
            "AI발전반대",
            "공학탐구"
          ]
        }
      ]
    },
    "10919": {
      "club": "프로토타입(공학)",
      "activities": [
        {
          "date": "2026",
          "type": "동아리",
          "title": "프로토타입 동아리 활동 - 공학 탐구 및 AI 독서토론",
          "summary": "프로토타입 동아리에서 기계공학과 진학을 목표로 활동함. 1차 활동에서 팀원들과 함께 도서를 통해 공학 분야 자료를 조사하고 희망학과 발표 활동에 참여함. 기계공학의 원리와 산업 활용 사례를 탐구하며 진로에 대한 이해를 심화하는 계기를 가짐. 2차 독서토론에서 『아이, 로봇』을 감상하고 AI 사용에 대한 찬반 논점을 탐색하며 인공지능 기술이 미래 사회와 기계공학 분야에 미치는 영향을 탐구함. 공학 분야의 다양한 가능성을 탐색하고 AI 기술에 대한 비판적 사고력을 기르는 동아리 활동을 수행함.",
          "keywords": [
            "기계공학",
            "AI독서토론",
            "아이로봇",
            "공학진로",
            "탐구활동"
          ]
        }
      ]
    },
    "11004": {
      "club": "프로토타입(공학)",
      "activities": [
        {
          "date": "2026",
          "type": "동아리",
          "title": "프로토타입 동아리 활동 - 공학 자료조사 및 AI 독서토론",
          "summary": "프로토타입 동아리에서 공학 계열 진학을 목표로 활동함. 1차 활동에서 도서를 통해 공학 분야 자료를 조사하고 팀 발표 활동에 기여하며 다양한 공학 분야의 원리와 직업 세계를 탐구함. 2차 독서토론에서 『아이, 로봇』을 감상하고 'AI의 무한한 발전'에 반대 입장을 취하여 AI 과발전이 초래할 수 있는 인간 자율성 침해와 사회적 문제를 논거로 제시함. 찬성 측의 AI 발전 이점 주장에 대해 기술 통제 가능성과 인간 중심 공학의 중요성을 강조하는 논리를 구성함. 공학 기술의 사회적 역할을 탐구하며 비판적 사고력을 기름.",
          "keywords": [
            "공학탐구",
            "AI독서토론",
            "아이로봇",
            "AI발전반대",
            "공학진로"
          ]
        }
      ]
    },
    "11011": {
      "club": "프로토타입(공학)",
      "activities": [
        {
          "date": "2026",
          "type": "동아리",
          "title": "프로토타입 동아리 활동 - 생명공학 발표 및 AI 독서토론",
          "summary": "프로토타입 동아리에서 항공정비사를 진로로 삼아 활동함. 1차 활동에서 『공학이란 무엇인가』의 생명공학 분야 내용을 발표 주제로 선택하여 생명공학 기술의 원리와 실제 적용 사례를 조사하고 발표함. 항공정비와 생명공학의 접점인 정밀 공학 기술을 탐구하며 공학 분야의 폭넓은 이해를 도모함. 2차 독서토론에서 『아이, 로봇』을 읽고 AI의 무한한 발전 찬성 입장을 취하여 AI가 이미 실생활에 깊이 자리 잡고 있으며 전문적 분야에서의 활용이 삶의 질을 향상시킨다는 논거를 제시함. AI 기술과 공학의 융합 가능성을 탐구하는 역량을 기름.",
          "keywords": [
            "생명공학",
            "항공정비",
            "AI독서토론",
            "아이로봇",
            "AI발전찬성"
          ]
        }
      ]
    },
    "11013": {
      "club": "프로토타입(공학)",
      "activities": [
        {
          "date": "2026",
          "type": "동아리",
          "title": "프로토타입 동아리 활동 - 생명화학공학 발표 및 AI 독서토론",
          "summary": "프로토타입 동아리에서 반도체공학자를 진로로 삼아 활동함. 1차 활동에서 '대한민국 헌법 제1조' 조의 발표에서 생명화학공학 기술의 사용 사례와 인슐린 생산 사례를 구체적으로 조사하는 역할을 담당하여 생명공학과 화학공학이 결합된 바이오 의약품 생산 원리를 탐구함. 2차 독서토론에서 『아이, 로봇』을 읽고 AI 무한 발전 반대 입장을 취하여 ①AI 발전으로 인한 인간 능력 퇴화 ②AI의 통제 불가능성 ③사회 구조 붕괴 가능성을 세 가지 논거로 체계적으로 구성하고 발표함. 공학 기술의 윤리적 한계를 탐구하며 비판적 사고력을 기름.",
          "keywords": [
            "생명화학공학",
            "인슐린",
            "AI독서토론",
            "아이로봇",
            "AI발전반대"
          ]
        }
      ]
    }
  }
}
